boa/__init__.py
boa/__main__.py
boa/__version__.py
boa/_doc_utils.py
boa/_version.py
boa/async_opt.py
boa/ax_instantiation_utils.py
boa/controller.py
boa/definitions.py
boa/instantiation_base.py
boa/logger.py
boa/metaclasses.py
boa/plot.py
boa/plotting.py
boa/registry.py
boa/runner.py
boa/scheduler.py
boa/storage.py
boa/template.py
boa/utils.py
boa/cli/__init__.py
boa/config/__init__.py
boa/config/__main__.py
boa/config/config.py
boa/config/converters.py
boa/metrics/__init__.py
boa/metrics/metric_funcs.py
boa/metrics/metrics.py
boa/metrics/modular_metric.py
boa/metrics/synthetic_funcs.py
boa/scripts/__init__.py
boa/scripts/moo.py
boa/scripts/moo.yaml
boa/scripts/run_branin.py
boa/scripts/script_wrappers.py
boa/scripts/synth_func_cli.py
boa/scripts/synth_func_config.yaml
boa/wrappers/__init__.py
boa/wrappers/base_wrapper.py
boa/wrappers/script_wrapper.py
boa/wrappers/synthetic_wrapper.py
boa/wrappers/wrapper_utils.py
boa_framework-0.11.0.dist-info/LICENSE
boa_framework-0.11.0.dist-info/METADATA
boa_framework-0.11.0.dist-info/WHEEL
boa_framework-0.11.0.dist-info/entry_points.txt
boa_framework-0.11.0.dist-info/top_level.txt
boa_framework-0.11.0.dist-info/RECORD
