Metadata-Version: 2.1
Name: boa-framework
Version: 0.11.0
Summary: Bayesian Optimization for Anything: A high-level Bayesian optimization framework and model wrapping tool. It provides an easy-to-use interface between models and the python libraries Ax and BoTorch.
Author-email: Madeline Scyphers <madelinescyphers@gmail.com>, Justine Missik <jemissik@gmail.com>
License: MIT
Project-URL: Source Code, https://github.com/madeline-scyphers/boa
Project-URL: Bug Tracker, https://github.com/madeline-scyphers/boa/issues
Project-URL: Documentation, http://boa-framework.readthedocs.io
Classifier: Development Status :: 4 - Beta
Classifier: Programming Language :: Python :: 3
Classifier: Programming Language :: Python :: 3.8
Classifier: Programming Language :: Python :: 3.9
Classifier: Programming Language :: Python :: 3.10
Classifier: Programming Language :: Python :: 3.11
Classifier: Operating System :: OS Independent
License-File: LICENSE
Requires-Dist: torch <3
Requires-Dist: numpy <2
Requires-Dist: pandas <3
Requires-Dist: scipy <2
Requires-Dist: scikit-learn <2
Requires-Dist: click <9
Requires-Dist: panel <2
Requires-Dist: plotly >=5.10.0
Requires-Dist: notebook >=5.3
Requires-Dist: ipywidgets >=7.5
Requires-Dist: ax-platform <=0.3.6,>=0.3.1
Requires-Dist: ruamel.yaml <1
Requires-Dist: attrs <24
Requires-Dist: jinja2 <4
Provides-Extra: dev
Requires-Dist: ax-platform ==0.3.6 ; extra == 'dev'
Requires-Dist: attr-utils ; extra == 'dev'
Requires-Dist: myst-nb ; extra == 'dev'
Requires-Dist: jupyter ; extra == 'dev'
Requires-Dist: r ; extra == 'dev'
Requires-Dist: r-jsonlite ; extra == 'dev'
Requires-Dist: invoke ; extra == 'dev'
Requires-Dist: pre-commit ; extra == 'dev'
Requires-Dist: pytest ; extra == 'dev'
Requires-Dist: pytest-cov ; extra == 'dev'
Requires-Dist: isort ; extra == 'dev'
Requires-Dist: black ==22.6.0 ; extra == 'dev'
Requires-Dist: flake8 ; extra == 'dev'
Requires-Dist: flakeheaven >=3.0.0 ; extra == 'dev'
Requires-Dist: sphinx <6,>=4.4 ; extra == 'dev'
Requires-Dist: pydata-sphinx-theme >=0.13.0 ; extra == 'dev'
Requires-Dist: sphinxext-remoteliteralinclude ; extra == 'dev'
